spharapy/__init__.py
spharapy/_types.py
spharapy/spectral_filters.py
spharapy/spharabasis.py
spharapy/spharafilter.py
spharapy/spharatransform.py
spharapy/trimesh.py
spharapy/datasets/__init__.py
spharapy/datasets/base.py
spharapy/datasets/data/eeg_256_channels_label.csv
spharapy/datasets/data/eeg_256_channels_sep_data.csv
spharapy/datasets/data/eeg_256_channels_tri.csv
spharapy/datasets/data/eeg_256_channels_vert.csv
spharapy/datasets/data/simple_mesh_tri.csv
spharapy/datasets/data/simple_mesh_vert.csv
spharapy/datasets/descr/eeg_256_channel_study.rst
spharapy/datasets/descr/minimal_triangular_mesh.rst
spharapy/datasets/descr/simple_triangular_mesh.rst
spharapy/examples/SpharaPy_example.py
spharapy/examples/plot_01_quick_start.py
spharapy/examples/plot_02_sphara_basis_eeg.py
spharapy/examples/plot_03_sphara_analysis_eeg.py
spharapy/examples/plot_04_sphara_filter_eeg.py
spharapy/examples/plot_05_BaCI2019_TrainingCourse4_SpharaPy_01.py
spharapy/examples/plot_05_BaCI2019_TrainingCourse4_SpharaPy_02.py
spharapy-1.3.0.dist-info/licenses/LICENSE
spharapy-1.3.0.dist-info/METADATA
spharapy-1.3.0.dist-info/WHEEL
spharapy-1.3.0.dist-info/top_level.txt
spharapy-1.3.0.dist-info/RECORD
