Metadata-Version: 2.4
Name: spharapy
Version: 1.3.0
Summary: SPHARA-based spatial harmonic analysis and filtering
Author-email: Uwe Graichen <uwe.graichen@kl.ac.at>
License-Expression: BSD-3-Clause
Project-URL: Homepage, https://gitlab.com/uwegra/spharapy
Project-URL: Documentation, https://spharapy.readthedocs.io/
Project-URL: Tracker, https://gitlab.com/uwegra/spharapy/-/issues
Classifier: Programming Language :: Python :: 3 :: Only
Classifier: Programming Language :: Python :: 3.10
Classifier: Programming Language :: Python :: 3.11
Classifier: Programming Language :: Python :: 3.12
Classifier: Programming Language :: Python :: 3.13
Requires-Python: >=3.10
License-File: LICENSE
Requires-Dist: numpy>=1.23.5
Requires-Dist: scipy>=1.14
Requires-Dist: matplotlib>=3.6
Dynamic: license-file
